cobertura_clover_transform/__init__.py
cobertura_clover_transform/converter.py
cobertura_clover_transform/transform.xslt
cobertura_clover_transform-1.1.4.post1.dist-info/DESCRIPTION.rst
cobertura_clover_transform-1.1.4.post1.dist-info/entry_points.txt
cobertura_clover_transform-1.1.4.post1.dist-info/METADATA
cobertura_clover_transform-1.1.4.post1.dist-info/metadata.json
cobertura_clover_transform-1.1.4.post1.dist-info/RECORD
cobertura_clover_transform-1.1.4.post1.dist-info/top_level.txt
cobertura_clover_transform-1.1.4.post1.dist-info/WHEEL
